tgzr/declare/__init__.py
tgzr/declare/__version__.py
tgzr/declare/enums.py
tgzr/declare/render_context.py
tgzr/declare/renderer.py
tgzr/declare/serialization.py
tgzr/declare/state_store.py
tgzr/declare/base/__init__.py
tgzr/declare/base/components.py
tgzr/declare/base/renderer.py
tgzr/declare/base/schema.py
tgzr/declare/default/__init__.py
tgzr/declare/default/schema.py
tgzr/declare/models/__init__.py
tgzr/declare/models/_base.py
tgzr/declare/models/property.py
tgzr/declare/models/root_schema.py
tgzr/declare/qt/__init__.py
tgzr/declare/qt/app.py
tgzr/declare/qt/renderer.py
tgzr/declare/qt/schema.py
tgzr/declare/qt/components/__init__.py
tgzr/declare/qt/components/_qt_utils.py
tgzr/declare/qt/components/containers.py
tgzr/declare/qt/components/controls.py
tgzr/declare/qt/components/elements.py
tgzr/declare/qt/components/item_view.py
tgzr/declare/qt/components/others.py
tgzr/declare/qt/components/widget.py
tgzr/declare/qt/demo/__main__.py
tgzr/declare/qt/demo/player_app/__init__.py
tgzr/declare/qt/demo/player_app/__main__.py
tgzr/declare/qt/demo/player_app/controler.py
tgzr/declare/qt/demo/player_app/playsound.py
tgzr/declare/qt/demo/player_app/assets/arrow.mp3
tgzr/declare/qt/demo/player_app/assets/explosion.mp3
tgzr/declare/qt/demo/player_app/assets/missile.mp3
tgzr/declare/qt/demo/player_app/assets/pop.mp3
tgzr/declare/qt/editor/__init__.py
tgzr/declare/qt/editor/__main__.py
tgzr/declare/qt/editor/components_view.py
tgzr/declare/qt/editor/doc_view.py
tgzr/declare/qt/editor/editor.py
tgzr/declare/qt/editor/render_view.py
tgzr/declare/qt/editor/text_view.py
tgzr.declare-0.0.1rc1.dist-info/METADATA
tgzr.declare-0.0.1rc1.dist-info/WHEEL
tgzr.declare-0.0.1rc1.dist-info/top_level.txt
tgzr.declare-0.0.1rc1.dist-info/RECORD
