Metadata-Version: 2.1
Name: tgzr.declare
Version: 0.0.1rc1
Summary: Component UI
Home-page: https://gitlab.com/TGZR/tgzr.declare
Author: Damien "dee" Coureau
Author-email: dee909@gmail.com
License: LGPLv3+
Platform: UNKNOWN
Classifier: Development Status :: 3 - Alpha
Requires-Python: >=3.7
Requires-Dist: six
Requires-Dist: pydantic
Provides-Extra: pyside2
Requires-Dist: PySide2 ; extra == 'pyside2'
Provides-Extra: dev
Requires-Dist: tox ; extra == 'dev'
Requires-Dist: pytest ; extra == 'dev'
Requires-Dist: pytest-cov ; extra == 'dev'
Requires-Dist: flake8 ; extra == 'dev'
Requires-Dist: black ; extra == 'dev'
Requires-Dist: twine ; extra == 'dev'
Provides-Extra: qtpy
Requires-Dist: qtpy ; extra == 'qtpy'
Requires-Dist: qtawesome ; extra == 'qtpy'
Requires-Dist: qt-material ; extra == 'qtpy'
Requires-Dist: markdown ; extra == 'qtpy'
Requires-Dist: pygments ; extra == 'qtpy'
